miracle/MIRACLE.py
miracle/__init__.py
miracle/logger.py
miracle/version.py
miracle/third_party/__init__.py
miracle/third_party/imputation_gain.py
miracle/third_party/imputation_knn.py
miracle/third_party/imputation_mean.py
miracle/third_party/imputation_mice.py
miracle/third_party/imputation_missforest.py
miracle_imputation-0.1.6.dist-info/LICENSE
miracle_imputation-0.1.6.dist-info/METADATA
miracle_imputation-0.1.6.dist-info/WHEEL
miracle_imputation-0.1.6.dist-info/top_level.txt
miracle_imputation-0.1.6.dist-info/RECORD
