Metadata-Version: 2.1
Name: miracle-imputation
Version: 0.1.6
Summary: Missing data Imputation Refinement And Causal LEarning
Home-page: https://github.com/trentkyono/MIRACLE
Author: Trent Kyono
Author-email: 
License: BSD-3-Clause
Classifier: Programming Language :: Python :: 3
Classifier: Topic :: Scientific/Engineering :: Artificial Intelligence
Classifier: Intended Audience :: Healthcare Industry
Classifier: License :: OSI Approved :: BSD License
Classifier: Operating System :: OS Independent
License-File: LICENSE
Requires-Dist: loguru
Requires-Dist: numpy
Requires-Dist: pandas
Requires-Dist: scikit-learn
Requires-Dist: tensorflow >=2.0
